{
  "id": 78,
  "name": "النبإ",
  "transliteration": "An-Naba",
  "translation": "The Tidings",
  "type": "meccan",
  "total_verses": 40,
  "verses": [
    {
      "id": 1,
      "text": "عَمَّ يَتَسَآءَلُونَ",
      "translation": "वे आपस में किस चीज़ के विषय में प्रश्न कर रहे हैं?",
      "transliteration": "AAamma yatasaaloona"
    },
    {
      "id": 2,
      "text": "عَنِ ٱلنَّبَإِ ٱلۡعَظِيمِ",
      "translation": "बहुत बड़ी सूचना के विषय में।",
      "transliteration": "AAani alnnabai alAAatheemi"
    },
    {
      "id": 3,
      "text": "ٱلَّذِي هُمۡ فِيهِ مُخۡتَلِفُونَ",
      "translation": "जिसमें वे मतभेद करने वाले हैं।",
      "transliteration": "Allathee hum feehi mukhtalifoona"
    },
    {
      "id": 4,
      "text": "كَلَّا سَيَعۡلَمُونَ",
      "translation": "हरगिज़ नहीं, शीघ्र ही वे जान लेंगे।",
      "transliteration": "Kalla sayaAAlamoona"
    },
    {
      "id": 5,
      "text": "ثُمَّ كَلَّا سَيَعۡلَمُونَ",
      "translation": "फिर हरगिज़ नहीं, शीघ्र ही वे जान लेंगे।",
      "transliteration": "Thumma kalla sayaAAlamoona"
    },
    {
      "id": 6,
      "text": "أَلَمۡ نَجۡعَلِ ٱلۡأَرۡضَ مِهَٰدٗا",
      "translation": "क्या हमने धरती को बिछौना नहीं बनाया?",
      "transliteration": "Alam najAAali alarda mihadan"
    },
    {
      "id": 7,
      "text": "وَٱلۡجِبَالَ أَوۡتَادٗا",
      "translation": "और पर्वतों को मेखें?",
      "transliteration": "Waaljibala awtadan"
    },
    {
      "id": 8,
      "text": "وَخَلَقۡنَٰكُمۡ أَزۡوَٰجٗا",
      "translation": "तथा हमने तुम्हें जोड़े-जोड़े पैदा किया।",
      "transliteration": "Wakhalaqnakum azwajan"
    },
    {
      "id": 9,
      "text": "وَجَعَلۡنَا نَوۡمَكُمۡ سُبَاتٗا",
      "translation": "तथा हमने तुम्हारी नींद को आराम (का साधन) बनाया।",
      "transliteration": "WajaAAalna nawmakum subatan"
    },
    {
      "id": 10,
      "text": "وَجَعَلۡنَا ٱلَّيۡلَ لِبَاسٗا",
      "translation": "और हमने रात को आवरण बनाया।",
      "transliteration": "WajaAAalna allayla libasan"
    },
    {
      "id": 11,
      "text": "وَجَعَلۡنَا ٱلنَّهَارَ مَعَاشٗا",
      "translation": "और हमने दिन को कमाने के लिए बनाया।",
      "transliteration": "WajaAAalna alnnahara maAAashan"
    },
    {
      "id": 12,
      "text": "وَبَنَيۡنَا فَوۡقَكُمۡ سَبۡعٗا شِدَادٗا",
      "translation": "तथा हमने तुम्हारे ऊपर सात मज़बूत (आकाश) बनाए।",
      "transliteration": "Wabanayna fawqakum sabAAan shidadan"
    },
    {
      "id": 13,
      "text": "وَجَعَلۡنَا سِرَاجٗا وَهَّاجٗا",
      "translation": "और हमने एक प्रकाशमान् तप्त दीप (सूर्य) बनाया।",
      "transliteration": "WajaAAalna sirajan wahhajan"
    },
    {
      "id": 14,
      "text": "وَأَنزَلۡنَا مِنَ ٱلۡمُعۡصِرَٰتِ مَآءٗ ثَجَّاجٗا",
      "translation": "और हमने बदलियों से मूसलाधार पानी उतारा।",
      "transliteration": "Waanzalna mina almuAAsirati maan thajjajan"
    },
    {
      "id": 15,
      "text": "لِّنُخۡرِجَ بِهِۦ حَبّٗا وَنَبَاتٗا",
      "translation": "ताकि हम उसके द्वारा अन्न और वनस्पति उगाएँ।",
      "transliteration": "Linukhrija bihi habban wanabatan"
    },
    {
      "id": 16,
      "text": "وَجَنَّـٰتٍ أَلۡفَافًا",
      "translation": "और घने-घने बाग़।",
      "transliteration": "Wajannatin alfafan"
    },
    {
      "id": 17,
      "text": "إِنَّ يَوۡمَ ٱلۡفَصۡلِ كَانَ مِيقَٰتٗا",
      "translation": "निःसंदेह निर्णय (फ़ैसले) का दिन एक नियत समय है।",
      "transliteration": "Inna yawma alfasli kana meeqatan"
    },
    {
      "id": 18,
      "text": "يَوۡمَ يُنفَخُ فِي ٱلصُّورِ فَتَأۡتُونَ أَفۡوَاجٗا",
      "translation": "जिस दिन सूर में फूँक मारी जाएगी, तो तुम दल के दल चले आओगे।",
      "transliteration": "Yawma yunfakhu fee alssoori fatatoona afwajan"
    },
    {
      "id": 19,
      "text": "وَفُتِحَتِ ٱلسَّمَآءُ فَكَانَتۡ أَبۡوَٰبٗا",
      "translation": "और आकाश खोल दिया जाएगा, तो उसमें द्वार ही द्वार हो जाएँगे।",
      "transliteration": "Wafutihati alssamao fakanat abwaban"
    },
    {
      "id": 20,
      "text": "وَسُيِّرَتِ ٱلۡجِبَالُ فَكَانَتۡ سَرَابًا",
      "translation": "और पर्वत चलाए जाएँगे, तो वे मरीचिका बन जाएँगे।",
      "transliteration": "Wasuyyirati aljibalu fakanat saraban"
    },
    {
      "id": 21,
      "text": "إِنَّ جَهَنَّمَ كَانَتۡ مِرۡصَادٗا",
      "translation": "निःसंदेह जहन्नम घात में है।",
      "transliteration": "Inna jahannama kanat mirsadan"
    },
    {
      "id": 22,
      "text": "لِّلطَّـٰغِينَ مَـَٔابٗا",
      "translation": "सरकशों का ठिकाना है।",
      "transliteration": "Lilttagheena maaban"
    },
    {
      "id": 23,
      "text": "لَّـٰبِثِينَ فِيهَآ أَحۡقَابٗا",
      "translation": "जिसमें वे अनगिनत वर्षों तक रहेंगे।",
      "transliteration": "Labitheena feeha ahqaban"
    },
    {
      "id": 24,
      "text": "لَّا يَذُوقُونَ فِيهَا بَرۡدٗا وَلَا شَرَابًا",
      "translation": "वे उसमें न कोई ठंड चखेंगे और न पीने की चीज़।",
      "transliteration": "La yathooqoona feeha bardan wala sharaban"
    },
    {
      "id": 25,
      "text": "إِلَّا حَمِيمٗا وَغَسَّاقٗا",
      "translation": "सिवाय अत्यंत गर्म पानी और बहती पीप के।",
      "transliteration": "Illa hameeman waghassaqan"
    },
    {
      "id": 26,
      "text": "جَزَآءٗ وِفَاقًا",
      "translation": "यह पूरा-पूरा बदला है।",
      "transliteration": "Jazaan wifaqan"
    },
    {
      "id": 27,
      "text": "إِنَّهُمۡ كَانُواْ لَا يَرۡجُونَ حِسَابٗا",
      "translation": "निःसंदेह वे हिसाब से नहीं डरते थे।",
      "transliteration": "Innahum kanoo la yarjoona hisaban"
    },
    {
      "id": 28,
      "text": "وَكَذَّبُواْ بِـَٔايَٰتِنَا كِذَّابٗا",
      "translation": "तथा उन्होंने हमारी आयतों को बुरी तरह झुठलाया।",
      "transliteration": "Wakaththaboo biayatina kiththaban"
    },
    {
      "id": 29,
      "text": "وَكُلَّ شَيۡءٍ أَحۡصَيۡنَٰهُ كِتَٰبٗا",
      "translation": "और हमने हर चीज़ को लिखकर संरक्षित कर रखा है।",
      "transliteration": "Wakulla shayin ahsaynahu kitaban"
    },
    {
      "id": 30,
      "text": "فَذُوقُواْ فَلَن نَّزِيدَكُمۡ إِلَّا عَذَابًا",
      "translation": "तो चखो, हम तुम्हारे लिए यातना ही अधिक करते रहेंगे।",
      "transliteration": "Fathooqoo falan nazeedakum illa AAathaban"
    },
    {
      "id": 31,
      "text": "إِنَّ لِلۡمُتَّقِينَ مَفَازًا",
      "translation": "निःसंदेह (अल्लाह से) डरने वालों के लिए सफलता है।",
      "transliteration": "Inna lilmuttaqeena mafazan"
    },
    {
      "id": 32,
      "text": "حَدَآئِقَ وَأَعۡنَٰبٗا",
      "translation": "बाग़ तथा अंगूर।",
      "transliteration": "Hadaiqa waaAAnaban"
    },
    {
      "id": 33,
      "text": "وَكَوَاعِبَ أَتۡرَابٗا",
      "translation": "और समान उम्र वाली नवयुवतियाँ।",
      "transliteration": "WakawaAAiba atraban"
    },
    {
      "id": 34,
      "text": "وَكَأۡسٗا دِهَاقٗا",
      "translation": "और छलकते हुए प्याले।",
      "transliteration": "Wakasan dihaqan"
    },
    {
      "id": 35,
      "text": "لَّا يَسۡمَعُونَ فِيهَا لَغۡوٗا وَلَا كِذَّـٰبٗا",
      "translation": "वे उसमें न तो कोई व्यर्थ बात सुनेंगे और न (एक दूसरे को) झुठलाना।",
      "transliteration": "La yasmaAAoona feeha laghwan wala kiththaban"
    },
    {
      "id": 36,
      "text": "جَزَآءٗ مِّن رَّبِّكَ عَطَآءً حِسَابٗا",
      "translation": "यह तुम्हारे पालनहार की ओर से बदले में ऐसा प्रदान है जो पर्याप्त होगा।",
      "transliteration": "Jazaan min rabbika AAataan hisaban"
    },
    {
      "id": 37,
      "text": "رَّبِّ ٱلسَّمَٰوَٰتِ وَٱلۡأَرۡضِ وَمَا بَيۡنَهُمَا ٱلرَّحۡمَٰنِۖ لَا يَمۡلِكُونَ مِنۡهُ خِطَابٗا",
      "translation": "जो आकाशों और धरती तथा उनके बीच की हर चीज़ का पालनहार है, अत्यंत दयावान् है। उससे बात करने का उन्हें अधिकार नहीं होगा।",
      "transliteration": "Rabbi alssamawati waalardi wama baynahuma alrrahmani la yamlikoona minhu khitaban"
    },
    {
      "id": 38,
      "text": "يَوۡمَ يَقُومُ ٱلرُّوحُ وَٱلۡمَلَـٰٓئِكَةُ صَفّٗاۖ لَّا يَتَكَلَّمُونَ إِلَّا مَنۡ أَذِنَ لَهُ ٱلرَّحۡمَٰنُ وَقَالَ صَوَابٗا",
      "translation": "जिस दिन रूह़ (जिबरील) तथा फ़रिश्ते पंक्तियों में खड़े होंगे, उससे केवल वही बात कर सकेगा जिसे रहमान (अल्लाह) आज्ञा देगा और वह ठीक बात कहेगा।",
      "transliteration": "Yawma yaqoomu alrroohu waalmalaikatu saffan la yatakallamoona illa man athina lahu alrrahmanu waqala sawaban"
    },
    {
      "id": 39,
      "text": "ذَٰلِكَ ٱلۡيَوۡمُ ٱلۡحَقُّۖ فَمَن شَآءَ ٱتَّخَذَ إِلَىٰ رَبِّهِۦ مَـَٔابًا",
      "translation": "यही (वह) दिन है जो सत्य है। अतः जो चाहे अपने पालनहार की ओर लौटने की जगह (ठिकाना) बना ले।",
      "transliteration": "Thalika alyawmu alhaqqu faman shaa ittakhatha ila rabbihi maaban"
    },
    {
      "id": 40,
      "text": "إِنَّآ أَنذَرۡنَٰكُمۡ عَذَابٗا قَرِيبٗا يَوۡمَ يَنظُرُ ٱلۡمَرۡءُ مَا قَدَّمَتۡ يَدَاهُ وَيَقُولُ ٱلۡكَافِرُ يَٰلَيۡتَنِي كُنتُ تُرَٰبَۢا",
      "translation": "निःसंदेह हमने तुम्हें एक निकट ही आने वाली यातना से डरा दिया है, जिस दिन मनुष्य देख लेगा, जो कुछ उसके दोनों हाथों ने आगे भेजा है, और काफिर कहेगा : ऐ काश कि मैं मिट्टी होता!",
      "transliteration": "Inna antharnakum AAathaban qareeban yawma yanthuru almaro ma qaddamat yadahu wayaqoolu alkafiru ya laytanee kuntu turaban"
    }
  ]
}